cmon2lib/__init__.py
cmon2lib/ccaldav/__init__.py
cmon2lib/ccaldav/caldav_next_day_planning_read.py
cmon2lib/cowui/__init__.py
cmon2lib/cowui/utils.py
cmon2lib/ctaiga/__init__.py
cmon2lib/ctaiga/taiga_project_functions.py
cmon2lib/ctaiga/taiga_user_functions.py
cmon2lib/logging_config.py
cmon2lib/utils/cmon_logging.py
cmon2lib-0.0.7.dist-info/LICENSE
cmon2lib-0.0.7.dist-info/METADATA
cmon2lib-0.0.7.dist-info/WHEEL
cmon2lib-0.0.7.dist-info/RECORD
