Metadata-Version: 2.3
Name: cmon2lib
Version: 0.0.7
Summary: my personal python library for convenient personalized functionality
Author: Simon Dorr
Author-email: simon@ich-bin-simon.de
Requires-Python: >=3.7,<4.0
Classifier: Programming Language :: Python :: 3
Classifier: License :: OSI Approved :: MIT License
Classifier: Operating System :: OS Independent
Provides-Extra: test
Requires-Dist: caldav (>=0.12.1)
Requires-Dist: loguru (>=0.7.3,<0.8.0)
Requires-Dist: pytest ; extra == "test"
Requires-Dist: pytest-cov ; extra == "test"
Requires-Dist: python-taiga (>=1.3.2,<2.0.0)
Project-URL: Homepage, https://github.com/cmon2/cmon2lib
